MANIFEST.in
README.md
setup.py
examples/__init__.py
examples/test_spider_one/__init__.py
examples/test_spider_one/items.py
examples/test_spider_one/middlewares.py
examples/test_spider_one/spiders/__init__.py
examples/test_spider_one/spiders/test_first_spiders.py
examples/tests/__init__.py
examples/tests/test_bloomFilter.py
examples/tests/test_download_corountine.py
examples/tests/test_middlewareManager.py
examples/tests/test_session.py
examples/tests/test_settings.py
sprite/__init__.py
sprite/crawl.py
sprite/exceptions.py
sprite/item.py
sprite/middlewaremanager.py
sprite/spider.py
sprite/core/__init__.py
sprite/core/engine.py
sprite/core/scheduler.py
sprite/core/download/__init__.py
sprite/core/download/connection.py
sprite/core/download/exceptions.py
sprite/core/download/headers.py
sprite/core/download/limits.py
sprite/core/download/parsers.py
sprite/core/download/pool.py
sprite/core/download/proxy.py
sprite/core/download/request.py
sprite/core/download/response.py
sprite/core/download/retries.py
sprite/core/download/session.py
sprite/core/download/tcp_helpers.py
sprite/core/download/url.py
sprite/http/__init__.py
sprite/http/cookies.py
sprite/http/headers.py
sprite/http/request/__init__.py
sprite/http/response/__init__.py
sprite/settings/__init__.py
sprite/settings/default_settings.py
sprite/utils/__init__.py
sprite/utils/asyncHandler.py
sprite/utils/coroutinePool.py
sprite/utils/datatypes.py
sprite/utils/decoders.py
sprite/utils/ip.py
sprite/utils/log.py
sprite/utils/pybloomfilter.py
sprite/utils/queues.py
sprite/utils/request.py
sprite/utils/rpc.py
spriterx.egg-info/PKG-INFO
spriterx.egg-info/SOURCES.txt
spriterx.egg-info/dependency_links.txt
spriterx.egg-info/requires.txt
spriterx.egg-info/top_level.txt